{
  "data": [
	{
		"id": 21,
		"deltaPosition": 1066
	},
	{
		"id": 22,
		"deltaPosition": -36
	},
	{
		"id": 23,
		"deltaPosition": -272
	},
	{
		"id": 24,
		"deltaPosition": 287
	},
	{
		"id": 25,
		"deltaPosition": 277
	},
	{
		"id": 26,
		"deltaPosition": -23
	},
	{
		"id": 31,
		"deltaPosition": -1038
	},
	{
		"id": 32,
		"deltaPosition": 56
	},
	{
		"id": 33,
		"deltaPosition": 286
	},
	{
		"id": 34,
		"deltaPosition": -440
	},
	{
		"id": 35,
		"deltaPosition": -282
	},
	{
		"id": 36,
		"deltaPosition": 45
	}
  ]
}
