{
  "data": [
	{
		"id": 21,
		"deltaPosition": 138
	},
	{
		"id": 22,
		"deltaPosition": -93
	},
	{
		"id": 23,
		"deltaPosition": 12
	},
	{
		"id": 24,
		"deltaPosition": 64
	},
	{
		"id": 25,
		"deltaPosition": 15
	},
	{
		"id": 26,
		"deltaPosition": 26
	},
	{
		"id": 31,
		"deltaPosition": -36
	},
	{
		"id": 32,
		"deltaPosition": -92
	},
	{
		"id": 33,
		"deltaPosition": 24
	},
	{
		"id": 34,
		"deltaPosition": -74
	},
	{
		"id": 35,
		"deltaPosition": 25
	},
	{
		"id": 36,
		"deltaPosition": -36
	}
  ]
}
